mopad/__init__.py
mopad/widget.py
mopad-0.4.0.dist-info/METADATA
mopad-0.4.0.dist-info/WHEEL
mopad-0.4.0.dist-info/licenses/LICENSE
mopad-0.4.0.dist-info/RECORD
