Metadata-Version: 2.4
Name: mopad
Version: 0.4.0
Summary: An anywidget that allows gamepad input in Marimo
Project-URL: Homepage, https://github.com/vincentwarmerdam/mopad
Project-URL: Repository, https://github.com/vincentwarmerdam/mopad
Project-URL: Issues, https://github.com/vincentwarmerdam/mopad/issues
Author: mopad contributors
License: MIT License
License-File: LICENSE
Classifier: Development Status :: 3 - Alpha
Classifier: Intended Audience :: Developers
Classifier: License :: OSI Approved :: MIT License
Classifier: Programming Language :: Python :: 3
Classifier: Programming Language :: Python :: 3.8
Classifier: Programming Language :: Python :: 3.9
Classifier: Programming Language :: Python :: 3.10
Classifier: Programming Language :: Python :: 3.11
Classifier: Programming Language :: Python :: 3.12
Classifier: Topic :: Scientific/Engineering :: Visualization
Classifier: Topic :: Software Development :: Libraries :: Python Modules
Requires-Python: >=3.8
Requires-Dist: anywidget>=0.9.0
Requires-Dist: traitlets
Provides-Extra: dev
Requires-Dist: build; extra == 'dev'
Requires-Dist: mypy; extra == 'dev'
Requires-Dist: pytest; extra == 'dev'
Requires-Dist: pytest-cov; extra == 'dev'
Requires-Dist: ruff; extra == 'dev'
Requires-Dist: twine; extra == 'dev'
